README.md
setup.py
tornado_apidoc/__init__.py
tornado_apidoc/apidoc.py
tornado_apidoc.egg-info/PKG-INFO
tornado_apidoc.egg-info/SOURCES.txt
tornado_apidoc.egg-info/dependency_links.txt
tornado_apidoc.egg-info/requires.txt
tornado_apidoc.egg-info/top_level.txt