Metadata-Version: 1.1
Name: tornado-apidoc
Version: 1.0.0
Summary: Adds ApiDoc support to Tornado
Home-page: https://github.com/wenhan-wu/tornado-apidoc
Author: Wenhan Wu
Author-email: sdwwh2259253@gmail.com
License: MIT
Keywords: tornado,apidoc,doc,documentation,rest,restful
Platform: UNKNOWN
Classifier: Development Status :: 5 - Production/Stable
Classifier: Intended Audience :: Developers
Classifier: Natural Language :: English
Classifier: Operating System :: OS Independent
Classifier: Programming Language :: Python
Classifier: Programming Language :: Python :: 3
Classifier: Programming Language :: Python :: 3.2
Classifier: Programming Language :: Python :: 3.3
Classifier: Programming Language :: Python :: 3.4
Classifier: Programming Language :: Python :: Implementation :: CPython
